dsp_tools/__init__.py
dsp_tools/cli/__init__.py
dsp_tools/cli/args.py
dsp_tools/cli/call_action.py
dsp_tools/cli/call_action_files_only.py
dsp_tools/cli/call_action_with_network.py
dsp_tools/cli/create_parsers.py
dsp_tools/cli/entry_point.py
dsp_tools/cli/utils.py
dsp_tools/clients/CLAUDE.md
dsp_tools/clients/__init__.py
dsp_tools/clients/authentication_client.py
dsp_tools/clients/authentication_client_live.py
dsp_tools/clients/connection.py
dsp_tools/clients/connection_live.py
dsp_tools/clients/fuseki_metrics.py
dsp_tools/clients/group_user_clients.py
dsp_tools/clients/group_user_clients_live.py
dsp_tools/clients/legal_info_client.py
dsp_tools/clients/legal_info_client_live.py
dsp_tools/clients/list_client.py
dsp_tools/clients/list_client_live.py
dsp_tools/clients/metadata_client.py
dsp_tools/clients/metadata_client_live.py
dsp_tools/clients/ontology_clients.py
dsp_tools/clients/ontology_create_client_live.py
dsp_tools/clients/ontology_get_client_live.py
dsp_tools/clients/permissions_client.py
dsp_tools/clients/project_client.py
dsp_tools/clients/project_client_live.py
dsp_tools/commands/__init__.py
dsp_tools/commands/create/CLAUDE.md
dsp_tools/commands/create/__init__.py
dsp_tools/commands/create/communicate_problems.py
dsp_tools/commands/create/create.py
dsp_tools/commands/create/create_on_server/__init__.py
dsp_tools/commands/create/create_on_server/cardinalities.py
dsp_tools/commands/create/create_on_server/classes.py
dsp_tools/commands/create/create_on_server/complete_ontologies.py
dsp_tools/commands/create/create_on_server/default_permissions.py
dsp_tools/commands/create/create_on_server/group_users.py
dsp_tools/commands/create/create_on_server/lists.py
dsp_tools/commands/create/create_on_server/mappers.py
dsp_tools/commands/create/create_on_server/onto_utils.py
dsp_tools/commands/create/create_on_server/ontology.py
dsp_tools/commands/create/create_on_server/project.py
dsp_tools/commands/create/create_on_server/properties.py
dsp_tools-18.5.0.dist-info/WHEEL
dsp_tools-18.5.0.dist-info/entry_points.txt
dsp_tools-18.5.0.dist-info/METADATA
dsp_tools-18.5.0.dist-info/RECORD
