Metadata-Version: 2.3
Name: dsp-tools
Version: 18.5.0
Summary: DSP-TOOLS is a Python package with a command line interface that helps you interact with a DaSCH service platform (DSP) server.
Author: DaSCH - Swiss National Data and Service Center for the Humanities
Author-email: DaSCH - Swiss National Data and Service Center for the Humanities <info@dasch.swiss>
Classifier: Programming Language :: Python :: 3.12
Classifier: Programming Language :: Python :: 3.13
Classifier: Programming Language :: Python :: 3.14
Classifier: License :: OSI Approved :: GNU General Public License v3 (GPLv3)
Classifier: Operating System :: OS Independent
Requires-Dist: argparse
Requires-Dist: jinja2
Requires-Dist: jsonpath-ng
Requires-Dist: jsonschema
Requires-Dist: loguru~=0.7.3
Requires-Dist: lxml
Requires-Dist: openpyxl
Requires-Dist: packaging
Requires-Dist: pandas[excel]
Requires-Dist: polars
Requires-Dist: pyld
Requires-Dist: pyoxigraph~=0.5.2
Requires-Dist: python-dotenv
Requires-Dist: pyyaml
Requires-Dist: rdflib
Requires-Dist: regex
Requires-Dist: requests
Requires-Dist: rustworkx~=0.17.1
Requires-Dist: tqdm
Requires-Dist: typing-extensions
Requires-Python: >=3.12
Project-URL: Documentation, https://docs.dasch.swiss/latest/DSP-TOOLS/
Project-URL: Homepage, https://www.dasch.swiss/
Project-URL: Repository, https://github.com/dasch-swiss/dsp-tools.git
